COPYING
MANIFEST.in
README.rst
bootstrap-buildout.py
buildout.cfg
setup.py
bob/__init__.py
bob.paper.SCIA2015.egg-info/PKG-INFO
bob.paper.SCIA2015.egg-info/SOURCES.txt
bob.paper.SCIA2015.egg-info/dependency_links.txt
bob.paper.SCIA2015.egg-info/entry_points.txt
bob.paper.SCIA2015.egg-info/requires.txt
bob.paper.SCIA2015.egg-info/top_level.txt
bob/paper/__init__.py
bob/paper/SCIA2015/__init__.py
bob/paper/SCIA2015/evaluate.py
bob/paper/SCIA2015/lbp_boosting.py
bob/paper/SCIA2015/pca_lda.py
bob/paper/SCIA2015/preprocess.py
bob/paper/SCIA2015/utils.py
bob/paper/SCIA2015/protocol/lfw/fold1/dev/for_models.lst
bob/paper/SCIA2015/protocol/lfw/fold1/dev/for_scores.lst
bob/paper/SCIA2015/protocol/lfw/fold1/eval/for_models.lst
bob/paper/SCIA2015/protocol/lfw/fold1/eval/for_scores.lst
bob/paper/SCIA2015/protocol/lfw/fold1/norm/train_optional_world_1.lst
bob/paper/SCIA2015/protocol/lfw/fold1/norm/train_optional_world_2.lst
bob/paper/SCIA2015/protocol/lfw/fold1/norm/train_world.lst
bob/paper/SCIA2015/protocol/lfw/fold2/dev/for_models.lst
bob/paper/SCIA2015/protocol/lfw/fold2/dev/for_scores.lst
bob/paper/SCIA2015/protocol/lfw/fold2/eval/for_models.lst
bob/paper/SCIA2015/protocol/lfw/fold2/eval/for_scores.lst
bob/paper/SCIA2015/protocol/lfw/fold2/norm/train_optional_world_1.lst
bob/paper/SCIA2015/protocol/lfw/fold2/norm/train_optional_world_2.lst
bob/paper/SCIA2015/protocol/lfw/fold2/norm/train_world.lst
bob/paper/SCIA2015/protocol/lfw/fold3/dev/for_models.lst
bob/paper/SCIA2015/protocol/lfw/fold3/dev/for_scores.lst
bob/paper/SCIA2015/protocol/lfw/fold3/eval/for_models.lst
bob/paper/SCIA2015/protocol/lfw/fold3/eval/for_scores.lst
bob/paper/SCIA2015/protocol/lfw/fold3/norm/train_optional_world_1.lst
bob/paper/SCIA2015/protocol/lfw/fold3/norm/train_optional_world_2.lst
bob/paper/SCIA2015/protocol/lfw/fold3/norm/train_world.lst
bob/paper/SCIA2015/protocol/lfw/fold4/dev/for_models.lst
bob/paper/SCIA2015/protocol/lfw/fold4/dev/for_scores.lst
bob/paper/SCIA2015/protocol/lfw/fold4/eval/for_models.lst
bob/paper/SCIA2015/protocol/lfw/fold4/eval/for_scores.lst
bob/paper/SCIA2015/protocol/lfw/fold4/norm/train_optional_world_1.lst
bob/paper/SCIA2015/protocol/lfw/fold4/norm/train_optional_world_2.lst
