Metadata-Version: 1.1
Name: bob.paper.SCIA2015
Version: 2.0.4
Summary: Source code for regenerating the results of the paper "Gender Classification by LUT based boosting of Overlapping Block Patterns"
Home-page: http://github.com/bioidiap/bob.paper.SCIA2015
Author: Manuel Gunther
Author-email: siebenkopf@googlemail.com
License: GPLv3
Keywords: bob,gender classification,boosting,OBP
Platform: UNKNOWN
Classifier: Framework :: Bob
Classifier: Development Status :: 4 - Beta
Classifier: Intended Audience :: Developers
Classifier: License :: OSI Approved :: GNU General Public License v3 (GPLv3)
Classifier: Natural Language :: English
Classifier: Programming Language :: Python
Classifier: Topic :: Scientific/Engineering :: Artificial Intelligence
